hush_push-0.3.0.dist-info/DESCRIPTION.rst
hush_push-0.3.0.dist-info/METADATA
hush_push-0.3.0.dist-info/RECORD
hush_push-0.3.0.dist-info/WHEEL
hush_push-0.3.0.dist-info/entry_points.txt
hush_push-0.3.0.dist-info/metadata.json
hush_push-0.3.0.dist-info/top_level.txt
hushpush/__init__.py
hushpush/cmd.py
hushpush/constant.py
hushpush/hushpush.py
hushpush/paraminfo.py
hushpush/prereqs.py
