Metadata-Version: 2.0
Name: hush-push
Version: 0.3.0
Summary: Push your git-secret protected configuration parameters to AWS Parameter Store using roles for multiple accounts
Home-page: https://github.com/hawry/hush-push
Author: hawry
Author-email: hawry@hawry.net
License: UNKNOWN
Platform: UNKNOWN
Classifier: Programming Language :: Python :: 3.5
Classifier: License :: OSI Approved :: MIT License
Classifier: Operating System :: POSIX :: Linux
Classifier: Development Status :: 3 - Alpha
Requires-Dist: argparse
Requires-Dist: boto3
Requires-Dist: coloredlogs
Requires-Dist: gitpython
Requires-Dist: terminaltables
